Metadata-Version: 1.0
Name: NG-distributions
Version: 0.1
Summary: Gaussian and Binomial distribution
Home-page: UNKNOWN
Author: Shivakant Vishwakarma
Author-email: shivakant7621@gmail.com
License: UNKNOWN
Platform: UNKNOWN
